dragonfly_dome/controller.py
lunaticoastro_dragonfly_controller-0.14.0.dist-info/LICENSE
lunaticoastro_dragonfly_controller-0.14.0.dist-info/METADATA
lunaticoastro_dragonfly_controller-0.14.0.dist-info/WHEEL
lunaticoastro_dragonfly_controller-0.14.0.dist-info/entry_points.txt
lunaticoastro_dragonfly_controller-0.14.0.dist-info/RECORD
