Metadata-Version: 2.1
Name: lunaticoastro-dragonfly-controller
Version: 0.14.0
Summary: Python Lib to control lunaticoastro dragonfly
Author: Robert Bradley
Author-email: robbrad182@gmail.com
Requires-Python: >=3.10,<4.0
Classifier: Programming Language :: Python :: 3
Classifier: Programming Language :: Python :: 3.10
Classifier: Programming Language :: Python :: 3.11
Requires-Dist: fastapi (>=0.111.0,<0.112.0)
Requires-Dist: uvicorn (>=0.29.0,<0.30.0)
Project-URL: issues, https://github.com/robbrad/lunaticoastro-dragonfly-controller/issues
